galpro/__init__.py
galpro/conf.py
galpro/model.py
galpro/plot.py
galpro/test.py
galpro/utils.py
galpro/validation.py
galpro-0.1.1.dist-info/LICENSE
galpro-0.1.1.dist-info/METADATA
galpro-0.1.1.dist-info/WHEEL
galpro-0.1.1.dist-info/top_level.txt
galpro-0.1.1.dist-info/RECORD
