Metadata-Version: 2.1
Name: galpro
Version: 0.1.1
Summary: Machine learning galaxy properties
Home-page: https://galpro.readthedocs.io/
Author: Sunil Mucesh
Author-email: smucesh@hotmail.co.uk
License: MIT License
Project-URL: readthedocs, https://galpro.readthedocs.io
Project-URL: GitHub, https://github.com/smucesh/galpro
Project-URL: arXiv, https://arxiv.org/abs/2012.05928
Platform: UNKNOWN
Requires-Dist: numpy
Requires-Dist: scikit-learn (>=0.22.1)
Requires-Dist: joblib
Requires-Dist: h5py
Requires-Dist: matplotlib
Requires-Dist: statsmodels (==0.11.0)
Requires-Dist: seaborn (==0.10.1)
Requires-Dist: scipy (>=1.6.0)
Requires-Dist: pandas
